MANIFEST.in
README.md
setup.py
harminv/__init__.py
harminv/_harminv.h
harminv/charminv.c
harminv/charminv.pxd
harminv/charminv.pyx
harminv/harminv.py
pharminv.egg-info/PKG-INFO
pharminv.egg-info/SOURCES.txt
pharminv.egg-info/dependency_links.txt
pharminv.egg-info/top_level.txt