Metadata-Version: 1.0
Name: pharminv
Version: 0.3
Summary: Python interface to harminv
Home-page: http://github.com/aaren/pharminv
Author: Aaron O'Leary
Author-email: dev@aaren.me
License: GPLv3
Platform: UNKNOWN
